toolreg/__init__.py
toolreg/py.typed
toolreg/dissect/__init__.py
toolreg/dissect/detect_docstring_style.py
toolreg/dissect/inspect_doc_style.py
toolreg/dissect/inspect_function.py
toolreg/registry/__init__.py
toolreg/registry/register_item.py
toolreg/registry/registry.py
toolreg/registry/tool.py
toolreg/registry/toolfile.py
toolreg/resources/filters.toml
toolreg/resources/icons.json.gzip
toolreg/tools/__init__.py
toolreg/tools/html.py
toolreg/tools/icon.py
toolreg/tools/inspection.py
toolreg/tools/iterate.py
toolreg/tools/llm.py
toolreg/tools/misc.py
toolreg/tools/mkdown.py
toolreg/tools/regex.py
toolreg/tools/serialize.py
toolreg/tools/tests.py
toolreg/tools/text.py
toolreg/utils/__init__.py
toolreg/utils/codetree.py
toolreg/utils/decorators.py
toolreg/utils/deepmerge.py
toolreg/utils/filetree.py
toolreg/utils/icons.py
toolreg/utils/resolve.py
toolreg-0.0.1.dist-info/METADATA
toolreg-0.0.1.dist-info/WHEEL
toolreg-0.0.1.dist-info/licenses/LICENSE
toolreg-0.0.1.dist-info/RECORD
