Metadata-Version: 2.3
Name: toolreg
Version: 0.0.1
Summary: A tool register.
Project-URL: Documentation, https://phil65.github.io/toolreg/
Project-URL: Source, https://github.com/phil65/toolreg
Author-email: Philipp Temminghoff <philipptemminghoff@googlemail.com>
License-Expression: MIT
License-File: LICENSE
Classifier: Development Status :: 4 - Beta
Classifier: Intended Audience :: Developers
Classifier: Operating System :: OS Independent
Classifier: Programming Language :: Python :: 3
Classifier: Programming Language :: Python :: 3 :: Only
Classifier: Programming Language :: Python :: 3.12
Classifier: Programming Language :: Python :: 3.13
Classifier: Programming Language :: Python :: 3.14
Classifier: Topic :: Documentation
Classifier: Topic :: Software Development
Classifier: Topic :: Utilities
Classifier: Typing :: Typed
Requires-Python: >=3.12
Requires-Dist: fsspec
Requires-Dist: jinja2
Requires-Dist: universal-pathlib
Provides-Extra: extras
Requires-Dist: black; extra == 'extras'
Requires-Dist: humanize; extra == 'extras'
Requires-Dist: natsort; extra == 'extras'
Requires-Dist: pygments; extra == 'extras'
Provides-Extra: icons
Requires-Dist: pyconify; extra == 'icons'
Provides-Extra: llm
Requires-Dist: litellm; extra == 'llm'
Requires-Dist: pillow; extra == 'llm'
Requires-Dist: python-dotenv; extra == 'llm'
Provides-Extra: yaml
Requires-Dist: yamling; extra == 'yaml'
